[
  {
    "TIME": "12:00",
    "STROBE": "JOB JOBSE",
    "MOON": "CHRIS SSG",
    "AURA": "L.B. DUB CORP B2B MARTYN",
    "FOREST RAVE": "MX. BLAIRE",
    "PIT": "DIRTYDMS B2B NESKA",
    "TUNNEL": "COSTANZA"
  },
  {
    "TIME": "12:15",
    "STROBE": "",
    "MOON": "",
    "AURA": "",
    "FOREST RAVE": "",
    "PIT": "",
    "TUNNEL": ""
  },
  {
    "TIME": "12:30",
    "STROBE": "",
    "MOON": "",
    "AURA": "",
    "FOREST RAVE": "",
    "PIT": "",
    "TUNNEL": ""
  },
  {
    "TIME": "12:45",
    "STROBE": "",
    "MOON": "",
    "AURA": "",
    "FOREST RAVE": "",
    "PIT": "",
    "TUNNEL": ""
  },
  {
    "TIME": "13:00",
    "STROBE": "",
    "MOON": "",
    "AURA": "",
    "FOREST RAVE": "",
    "PIT": "",
    "TUNNEL": ""
  },
  {
    "TIME": "13:15",
    "STROBE": "",
    "MOON": "",
    "AURA": "",
    "FOREST RAVE": "",
    "PIT": "",
    "TUNNEL": ""
  },
  {
    "TIME": "13:30",
    "STROBE": "",
    "MOON": "",
    "AURA": "",
    "FOREST RAVE": "",
    "PIT": "",
    "TUNNEL": ""
  },
  {
    "TIME": "13:45",
    "STROBE": "",
    "MOON": "",
    "AURA": "",
    "FOREST RAVE": "",
    "PIT": "",
    "TUNNEL": ""
  },
  {
    "TIME": "14:00",
    "STROBE": "",
    "MOON": "",
    "AURA": "",
    "FOREST RAVE": "",
    "PIT": "",
    "TUNNEL": ""
  },
  {
    "TIME": "14:15",
    "STROBE": "",
    "MOON": "",
    "AURA": "",
    "FOREST RAVE": "",
    "PIT": "",
    "TUNNEL": ""
  },
  {
    "TIME": "14:30",
    "STROBE": "",
    "MOON": "",
    "AURA": "",
    "FOREST RAVE": "",
    "PIT": "TATYANA JANE",
    "TUNNEL": "LAIMA ADELAIDE (LIVE)"
  },
  {
    "TIME": "14:45",
    "STROBE": "",
    "MOON": "",
    "AURA": "",
    "FOREST RAVE": "",
    "PIT": "",
    "TUNNEL": ""
  },
  {
    "TIME": "15:00",
    "STROBE": "",
    "MOON": "",
    "AURA": "",
    "FOREST RAVE": "EOIN DJ",
    "PIT": "",
    "TUNNEL": ""
  },
  {
    "TIME": "15:15",
    "STROBE": "",
    "MOON": "",
    "AURA": "",
    "FOREST RAVE": "",
    "PIT": "",
    "TUNNEL": ""
  },
  {
    "TIME": "15:30",
    "STROBE": "",
    "MOON": "XIAOLIN (LIVE)",
    "AURA": "MORITZ VON OSWALD WITH AZU TIWALINE & TIKIMAN (LIVE)",
    "FOREST RAVE": "",
    "PIT": "",
    "TUNNEL": "IGNEZ"
  },
  {
    "TIME": "15:45",
    "STROBE": "",
    "MOON": "",
    "AURA": "",
    "FOREST RAVE": "",
    "PIT": "",
    "TUNNEL": ""
  },
  {
    "TIME": "16:00",
    "STROBE": "",
    "MOON": "",
    "AURA": "",
    "FOREST RAVE": "",
    "PIT": "",
    "TUNNEL": ""
  },
  {
    "TIME": "16:15",
    "STROBE": "",
    "MOON": "",
    "AURA": "",
    "FOREST RAVE": "",
    "PIT": "",
    "TUNNEL": ""
  },
  {
    "TIME": "16:30",
    "STROBE": "INVT (LIVE)",
    "MOON": "KONDUKU B2B PLO MAN",
    "AURA": "",
    "FOREST RAVE": "",
    "PIT": "KAMPIRE B2B TASH LC",
    "TUNNEL": ""
  },
  {
    "TIME": "16:45",
    "STROBE": "",
    "MOON": "",
    "AURA": "",
    "FOREST RAVE": "",
    "PIT": "",
    "TUNNEL": ""
  },
  {
    "TIME": "17:00",
    "STROBE": "",
    "MOON": "",
    "AURA": "PEVERELIST B2B PINCH",
    "FOREST RAVE": "ERIS DREW B2B MARK FARINA",
    "PIT": "",
    "TUNNEL": ""
  },
  {
    "TIME": "17:15",
    "STROBE": "",
    "MOON": "",
    "AURA": "",
    "FOREST RAVE": "",
    "PIT": "",
    "TUNNEL": ""
  },
  {
    "TIME": "17:30",
    "STROBE": "LSDXOXO B2B SEGA BODEGA",
    "MOON": "",
    "AURA": "",
    "FOREST RAVE": "",
    "PIT": "",
    "TUNNEL": "JULIEN P & MAX WATTS (LIVE)"
  },
  {
    "TIME": "17:45",
    "STROBE": "",
    "MOON": "",
    "AURA": "",
    "FOREST RAVE": "",
    "PIT": "",
    "TUNNEL": ""
  },
  {
    "TIME": "18:00",
    "STROBE": "",
    "MOON": "",
    "AURA": "",
    "FOREST RAVE": "",
    "PIT": "",
    "TUNNEL": ""
  },
  {
    "TIME": "18:15",
    "STROBE": "",
    "MOON": "",
    "AURA": "",
    "FOREST RAVE": "",
    "PIT": "",
    "TUNNEL": ""
  },
  {
    "TIME": "18:30",
    "STROBE": "",
    "MOON": "",
    "AURA": "",
    "FOREST RAVE": "",
    "PIT": "TOUMBA X BIG MURK LIVE",
    "TUNNEL": "HELENA HAUFF B2B JULIANA HUXTABLE"
  },
  {
    "TIME": "18:45",
    "STROBE": "",
    "MOON": "",
    "AURA": "",
    "FOREST RAVE": "",
    "PIT": "",
    "TUNNEL": ""
  },
  {
    "TIME": "19:00",
    "STROBE": "",
    "MOON": "NATHAN FAKE (LIVE)",
    "AURA": "NÍDIA & VALENTINA (LIVE)",
    "FOREST RAVE": "",
    "PIT": "",
    "TUNNEL": ""
  },
  {
    "TIME": "19:15",
    "STROBE": "",
    "MOON": "",
    "AURA": "",
    "FOREST RAVE": "",
    "PIT": "",
    "TUNNEL": ""
  },
  {
    "TIME": "19:30",
    "STROBE": "",
    "MOON": "",
    "AURA": "",
    "FOREST RAVE": "",
    "PIT": "BEN UFO B2B PARIAH",
    "TUNNEL": ""
  },
  {
    "TIME": "19:45",
    "STROBE": "LINGUA EROTICA (LIVE)",
    "MOON": "",
    "AURA": "CCL B2B YUSHH",
    "FOREST RAVE": "",
    "PIT": "",
    "TUNNEL": ""
  },
  {
    "TIME": "20:00",
    "STROBE": "",
    "MOON": "POWDER",
    "AURA": "",
    "FOREST RAVE": "MR. G (LIVE)",
    "PIT": "",
    "TUNNEL": ""
  },
  {
    "TIME": "20:15",
    "STROBE": "",
    "MOON": "",
    "AURA": "",
    "FOREST RAVE": "",
    "PIT": "",
    "TUNNEL": ""
  },
  {
    "TIME": "20:30",
    "STROBE": "NENE H B2B U.R.TRAX",
    "MOON": "",
    "AURA": "",
    "FOREST RAVE": "",
    "PIT": "",
    "TUNNEL": "BASSIANI FOR RESISTANCE (HVL X NDRX X PHILIPPA PACHO)"
  },
  {
    "TIME": "20:45",
    "STROBE": "",
    "MOON": "",
    "AURA": "",
    "FOREST RAVE": "",
    "PIT": "",
    "TUNNEL": ""
  },
  {
    "TIME": "21:00",
    "STROBE": "",
    "MOON": "",
    "AURA": "",
    "FOREST RAVE": "CASSY B2B FREDDY K",
    "PIT": "",
    "TUNNEL": ""
  },
  {
    "TIME": "21:15",
    "STROBE": "",
    "MOON": "",
    "AURA": "",
    "FOREST RAVE": "",
    "PIT": "",
    "TUNNEL": ""
  },
  {
    "TIME": "21:30",
    "STROBE": "",
    "MOON": "",
    "AURA": "",
    "FOREST RAVE": "",
    "PIT": "GIGI FM B2B SHERELLE",
    "TUNNEL": ""
  },
  {
    "TIME": "21:45",
    "STROBE": "",
    "MOON": "",
    "AURA": "",
    "FOREST RAVE": "",
    "PIT": "",
    "TUNNEL": ""
  },
  {
    "TIME": "22:00",
    "STROBE": "",
    "MOON": "OMA TOTEM (LIVE)",
    "AURA": "SCRATCHCLART X TOYA DELAZY (LIVE)",
    "FOREST RAVE": "",
    "PIT": "",
    "TUNNEL": ""
  },
  {
    "TIME": "22:15",
    "STROBE": "",
    "MOON": "",
    "AURA": "",
    "FOREST RAVE": "",
    "PIT": "",
    "TUNNEL": ""
  },
  {
    "TIME": "22:30",
    "STROBE": "BENNY RODRIGUES B2B CARISTA",
    "MOON": "",
    "AURA": "",
    "FOREST RAVE": "",
    "PIT": "",
    "TUNNEL": "SPEKKI WEBU B2B TAKAAKI ITOH"
  },
  {
    "TIME": "22:45",
    "STROBE": "",
    "MOON": "WATA IGARASHI",
    "AURA": "",
    "FOREST RAVE": "",
    "PIT": "",
    "TUNNEL": ""
  },
  {
    "TIME": "23:00",
    "STROBE": "",
    "MOON": "",
    "AURA": "JOY ORBISON",
    "FOREST RAVE": "HERVÉ",
    "PIT": "",
    "TUNNEL": ""
  },
  {
    "TIME": "23:15",
    "STROBE": "",
    "MOON": "",
    "AURA": "",
    "FOREST RAVE": "",
    "PIT": "",
    "TUNNEL": ""
  },
  {
    "TIME": "23:30",
    "STROBE": "",
    "MOON": "",
    "AURA": "",
    "FOREST RAVE": "",
    "PIT": "CLARK (LIVE)",
    "TUNNEL": ""
  },
  {
    "TIME": "23:45",
    "STROBE": "",
    "MOON": "",
    "AURA": "",
    "FOREST RAVE": "",
    "PIT": "",
    "TUNNEL": ""
  },
  {
    "TIME": "0:00",
    "STROBE": "",
    "MOON": "",
    "AURA": "",
    "FOREST RAVE": "",
    "PIT": "",
    "TUNNEL": ""
  },
  {
    "TIME": "0:15",
    "STROBE": "",
    "MOON": "",
    "AURA": "",
    "FOREST RAVE": "",
    "PIT": "",
    "TUNNEL": ""
  },
  {
    "TIME": "0:30",
    "STROBE": "END",
    "MOON": "END",
    "AURA": "END",
    "FOREST RAVE": "END",
    "PIT": "END",
    "TUNNEL": "END"
  }
]
